LICENSE
README.rst
requirements.txt
setup.py
fastapi_icontract/__init__.py
fastapi_icontract/_decorators.py
fastapi_icontract/_globals.py
fastapi_icontract/openapi.py
fastapi_icontract/py.typed
fastapi_icontract/swagger_ui.py
fastapi_icontract.egg-info/PKG-INFO
fastapi_icontract.egg-info/SOURCES.txt
fastapi_icontract.egg-info/dependency_links.txt
fastapi_icontract.egg-info/requires.txt
fastapi_icontract.egg-info/top_level.txt
tests_3_8/__init__.py
tests_3_8/example_async.py
tests_3_8/test_example_async.py
tests_3_8/test_postcondition_async.py
tests_3_8/test_precondition_async.py
tests_3_8/test_snapshot_async.py