Metadata-Version: 2.1
Name: fastapi-icontract
Version: 0.0.4
Summary: Specify contracts for FastAPI endpoints.
Home-page: https://github.com/mristin/fastapi-icontract
Author: Marko Ristin
Author-email: marko@ristin.ch
License: License :: OSI Approved :: MIT License
Keywords: design-by-contract contracts automatic testing property-based
Platform: UNKNOWN
Classifier: Development Status :: 3 - Alpha
Classifier: License :: OSI Approved :: MIT License
Classifier: Programming Language :: Python :: 3.6
Classifier: Programming Language :: Python :: 3.7
Classifier: Programming Language :: Python :: 3.8
Classifier: Programming Language :: Python :: 3.9
Classifier: Programming Language :: Python :: 3.10
Classifier: Framework :: FastAPI
Provides-Extra: dev
License-File: LICENSE
